ai_dan.cpython-312-darwin.so
ai_dan_core-0.1.4.dist-info/RECORD
ai_dan_core-0.1.4.dist-info/WHEEL
ai_dan_core-0.1.4.dist-info/METADATA
