Metadata-Version: 2.2
Name: ai-dan-core
Version: 0.1.4
Summary: CPU-based neural network library written in C++
Keywords: neural-network,deep-learning,machine-learning,mnist,cpp
Author-Email: Aidan <aidann.mackey@gmail.com>
License: MIT
Classifier: Development Status :: 3 - Alpha
Classifier: Intended Audience :: Developers
Classifier: Intended Audience :: Science/Research
Classifier: License :: OSI Approved :: MIT License
Classifier: Programming Language :: C++
Classifier: Programming Language :: Python :: 3
Classifier: Programming Language :: Python :: 3.8
Classifier: Programming Language :: Python :: 3.9
Classifier: Programming Language :: Python :: 3.10
Classifier: Programming Language :: Python :: 3.11
Classifier: Programming Language :: Python :: 3.12
Classifier: Topic :: Scientific/Engineering :: Artificial Intelligence
Project-URL: Homepage, https://github.com/A-Mackey/ai-dan-core
Project-URL: Repository, https://github.com/A-Mackey/ai-dan-core
Project-URL: Issues, https://github.com/A-Mackey/ai-dan-core/issues
Requires-Python: >=3.8
